[
    {
        "category": "Digital Business & IT",
        "url": "https://executive.mit.edu/course-finder",
        "parent_url": "https://executive.mit.edu"
    },
    {
        "category": "Organizations & Leadership",
        "url": "https://executive.mit.edu/course-finder",
        "parent_url": "https://executive.mit.edu"
    },
    {
        "category": "Strategy & Innovation",
        "url": "https://executive.mit.edu/course-finder",
        "parent_url": "https://executive.mit.edu"
    },
    {
        "category": "Business Analytics",
        "url": "https://executive.mit.edu/course-finder",
        "parent_url": "https://executive.mit.edu"
    },
    {
        "category": "Negotiation & Communication",
        "url": "https://executive.mit.edu/course-finder",
        "parent_url": "https://executive.mit.edu"
    },
    {
        "category": "Systems Thinking",
        "url": "https://executive.mit.edu/course-finder",
        "parent_url": "https://executive.mit.edu"
    },
    {
        "category": "Financial Management",
        "url": "https://executive.mit.edu/course-finder",
        "parent_url": "https://executive.mit.edu"
    },
    {
        "category": "Marketing",
        "url": "https://executive.mit.edu/course-finder",
        "parent_url": "https://executive.mit.edu"
    },
    {
        "category": "Operations",
        "url": "https://executive.mit.edu/course-finder",
        "parent_url": "https://executive.mit.edu"
    },
    {
        "category": "Global Economics & Markets",
        "url": "https://executive.mit.edu/course-finder",
        "parent_url": "https://executive.mit.edu"
    },
    {
        "category": "Entrepreneurship",
        "url": "https://executive.mit.edu/course-finder",
        "parent_url": "https://executive.mit.edu"
    },
    {
        "category": "* This course is not focused on the features or selection of specific Industrial Internet of Things/IIoT technology products or services. Instead, it is intended to help senior leaders in manufacturing and operations who are deploying Industrial Internet of Things technologies to obtain greater value from their businesses by diagnosing the states of their systems, measuring activities appropriately, and overcoming cultural obstacles to deployment of productive technologies.",
        "url": "https://executive.mit.edu/course-finder",
        "parent_url": "https://executive.mit.edu"
    },
    {
        "category": "You will receive a certificate of course completion at the conclusion of this course. You may also be interested in our Executive Certificates which are designed around a central themed track and consist of several courses. Learn more.",
        "url": "https://executive.mit.edu/course-finder",
        "parent_url": "https://executive.mit.edu"
    },
    {
        "category": "Family Enterprise",
        "url": "https://executive.mit.edu/course-finder",
        "parent_url": "https://executive.mit.edu"
    }
]